LICENSE
README.md
setup.py
src/genbenchQC/__init__.py
src/genbenchQC/evaluate_dataset.py
src/genbenchQC/evaluate_sequences.py
src/genbenchQC/evaluate_split.py
src/genbenchQC.egg-info/PKG-INFO
src/genbenchQC.egg-info/SOURCES.txt
src/genbenchQC.egg-info/dependency_links.txt
src/genbenchQC.egg-info/entry_points.txt
src/genbenchQC.egg-info/requires.txt
src/genbenchQC.egg-info/top_level.txt
src/genbenchQC/report/__init__.py
src/genbenchQC/report/dataset_html_report.py
src/genbenchQC/report/dataset_plots.py
src/genbenchQC/report/report_common.py
src/genbenchQC/report/report_generator.py
src/genbenchQC/report/sequence_html_report.py
src/genbenchQC/report/sequences_plots.py
src/genbenchQC/report/split_html_report.py
src/genbenchQC/utils/__init__.py
src/genbenchQC/utils/bias_model.py
src/genbenchQC/utils/input_utils.py
src/genbenchQC/utils/statistics.py
src/genbenchQC/utils/testing.py