Metadata-Version: 2.4
Name: genbenchQC
Version: 1.0.2
Summary: Genomic Benchmarks QC: Automated Quality Control for Genomic Machine Learning Datasets
Author: Katarina Gresova
Author-email: gresova11@gmail.com
Keywords: genomic benchmarks,deep learning,machine learning,computational biology,bioinformatics,genomics,quality control
Classifier: Development Status :: 3 - Alpha
Classifier: Intended Audience :: Developers
Classifier: Topic :: Software Development :: Build Tools
Classifier: License :: OSI Approved :: MIT License
Classifier: Programming Language :: Python :: 3.8
Classifier: Programming Language :: Python :: 3.9
Classifier: Programming Language :: Python :: 3.10
License-File: LICENSE
Requires-Dist: numpy>=1.23
Requires-Dist: pandas>=1.5
Requires-Dist: matplotlib>=3.6
Requires-Dist: seaborn>=0.12
Requires-Dist: biopython>=1.8
Requires-Dist: scikit-learn>=1.2
Requires-Dist: cdhit-reader==0.2.0
Requires-Dist: statsmodels>=0.13
Provides-Extra: develop
Requires-Dist: pytest>=3; extra == "develop"
Dynamic: author
Dynamic: author-email
Dynamic: classifier
Dynamic: description
Dynamic: description-content-type
Dynamic: keywords
Dynamic: license-file
Dynamic: provides-extra
Dynamic: requires-dist
Dynamic: summary
